{
  "annotations": {
    "list": [
      {
        "builtIn": 1,
        "datasource": {
          "type": "grafana",
          "uid": "-- Grafana --"
        },
        "enable": true,
        "hide": true,
        "iconColor": "rgba(0, 211, 255, 1)",
        "name": "Annotations & Alerts",
        "type": "dashboard"
      }
    ]
  },
  "editable": true,
  "fiscalYearStartMonth": 0,
  "graphTooltip": 0,
  "id": 1,
  "links": [],
  "panels": [
    {
      "gridPos": {
        "h": 1,
        "w": 24,
        "x": 0,
        "y": 0
      },
      "id": 25,
      "title": "Kitchen",
      "type": "row"
    },
    {
      "datasource": {
        "default": true,
        "type": "prometheus",
        "uid": "ce6lrrt58z4zkc"
      },
      "description": "",
      "fieldConfig": {
        "defaults": {
          "color": {
            "mode": "palette-classic"
          },
          "custom": {
            "axisBorderShow": false,
            "axisCenteredZero": false,
            "axisColorMode": "text",
            "axisLabel": "",
            "axisPlacement": "auto",
            "barAlignment": 0,
            "barWidthFactor": 0.6,
            "drawStyle": "line",
            "fillOpacity": 0,
            "gradientMode": "none",
            "hideFrom": {
              "legend": false,
              "tooltip": false,
              "viz": false
            },
            "insertNulls": false,
            "lineInterpolation": "linear",
            "lineStyle": {
              "fill": "solid"
            },
            "lineWidth": 1,
            "pointSize": 5,
            "scaleDistribution": {
              "type": "linear"
            },
            "showPoints": "auto",
            "spanNulls": false,
            "stacking": {
              "group": "A",
              "mode": "none"
            },
            "thresholdsStyle": {
              "mode": "off"
            }
          },
          "mappings": [],
          "thresholds": {
            "mode": "absolute",
            "steps": [
              {
                "color": "green",
                "value": null
              },
              {
                "color": "red",
                "value": 80
              }
            ]
          }
        },
        "overrides": []
      },
      "gridPos": {
        "h": 8,
        "w": 12,
        "x": 0,
        "y": 1
      },
      "id": 24,
      "options": {
        "legend": {
          "calcs": [],
          "displayMode": "list",
          "placement": "bottom",
          "showLegend": true
        },
        "tooltip": {
          "mode": "single",
          "sort": "none"
        }
      },
      "targets": [
        {
          "datasource": {
            "type": "prometheus"
          },
          "editorMode": "code",
          "expr": "sum by (uri)(histogram_quantile(0.99, sum(rate(http_server_requests_seconds_bucket{ status!~\"5..\", job=\"orbilnot-kitchen\"}[1m])) by (le)))",
          "hide": false,
          "instant": false,
          "legendFormat": "__auto",
          "range": true,
          "refId": "99_latency"
        },
        {
          "datasource": {
            "type": "prometheus"
          },
          "editorMode": "code",
          "expr": "sum by (uri) (histogram_quantile(0.95, sum(rate(http_server_requests_seconds_bucket{ status!~\"5..\", uri=~\"/user.*\"}[1m])) by (le)))",
          "hide": false,
          "instant": false,
          "legendFormat": "__auto",
          "range": true,
          "refId": "95_latency"
        },
        {
          "datasource": {
            "type": "prometheus"
          },
          "editorMode": "code",
          "expr": "sum by (uri) (histogram_quantile(0.50, sum(rate(http_server_requests_seconds_bucket{ status!~\"5..\", uri=~\"/user.*\"}[1m])) by (le)))",
          "hide": false,
          "instant": false,
          "legendFormat": "__auto",
          "range": true,
          "refId": "50_latency"
        }
      ],
      "title": "latency",
      "type": "timeseries"
    },
    {
      "datasource": {
        "default": true,
        "type": "prometheus",
        "uid": "ce6lrrt58z4zkc"
      },
      "description": "",
      "fieldConfig": {
        "defaults": {
          "color": {
            "mode": "palette-classic"
          },
          "custom": {
            "axisBorderShow": false,
            "axisCenteredZero": false,
            "axisColorMode": "text",
            "axisLabel": "",
            "axisPlacement": "auto",
            "barAlignment": 0,
            "barWidthFactor": 0.6,
            "drawStyle": "line",
            "fillOpacity": 0,
            "gradientMode": "none",
            "hideFrom": {
              "legend": false,
              "tooltip": false,
              "viz": false
            },
            "insertNulls": false,
            "lineInterpolation": "linear",
            "lineWidth": 1,
            "pointSize": 5,
            "scaleDistribution": {
              "type": "linear"
            },
            "showPoints": "auto",
            "spanNulls": false,
            "stacking": {
              "group": "A",
              "mode": "none"
            },
            "thresholdsStyle": {
              "mode": "off"
            }
          },
          "mappings": [],
          "thresholds": {
            "mode": "absolute",
            "steps": [
              {
                "color": "green",
                "value": null
              },
              {
                "color": "red",
                "value": 80
              }
            ]
          }
        },
        "overrides": []
      },
      "gridPos": {
        "h": 8,
        "w": 12,
        "x": 0,
        "y": 9
      },
      "id": 22,
      "options": {
        "legend": {
          "calcs": [],
          "displayMode": "list",
          "placement": "bottom",
          "showLegend": true
        },
        "tooltip": {
          "mode": "single",
          "sort": "none"
        }
      },
      "targets": [
        {
          "datasource": {
            "type": "prometheus"
          },
          "disableTextWrap": false,
          "editorMode": "code",
          "expr": "irate(http_server_requests_seconds_count{job=\"orbilnot-kitchen\"}[30s])",
          "fullMetaSearch": false,
          "includeNullMetadata": true,
          "instant": false,
          "legendFormat": "__auto",
          "range": true,
          "refId": "A",
          "useBackend": false
        }
      ],
      "title": "RPS",
      "type": "timeseries"
    },
    {
      "datasource": {
        "default": true,
        "type": "prometheus",
        "uid": "ce6lrrt58z4zkc"
      },
      "description": "",
      "fieldConfig": {
        "defaults": {
          "color": {
            "mode": "palette-classic"
          },
          "custom": {
            "axisBorderShow": false,
            "axisCenteredZero": false,
            "axisColorMode": "text",
            "axisLabel": "",
            "axisPlacement": "auto",
            "barAlignment": 0,
            "barWidthFactor": 0.6,
            "drawStyle": "line",
            "fillOpacity": 0,
            "gradientMode": "none",
            "hideFrom": {
              "legend": false,
              "tooltip": false,
              "viz": false
            },
            "insertNulls": false,
            "lineInterpolation": "linear",
            "lineWidth": 1,
            "pointSize": 5,
            "scaleDistribution": {
              "type": "linear"
            },
            "showPoints": "auto",
            "spanNulls": false,
            "stacking": {
              "group": "A",
              "mode": "none"
            },
            "thresholdsStyle": {
              "mode": "off"
            }
          },
          "mappings": [],
          "thresholds": {
            "mode": "absolute",
            "steps": [
              {
                "color": "green",
                "value": null
              },
              {
                "color": "red",
                "value": 80
              }
            ]
          }
        },
        "overrides": []
      },
      "gridPos": {
        "h": 8,
        "w": 12,
        "x": 0,
        "y": 17
      },
      "id": 20,
      "options": {
        "legend": {
          "calcs": [],
          "displayMode": "list",
          "placement": "bottom",
          "showLegend": true
        },
        "tooltip": {
          "mode": "single",
          "sort": "none"
        }
      },
      "targets": [
        {
          "datasource": {
            "type": "prometheus"
          },
          "editorMode": "code",
          "expr": "irate(http_server_requests_seconds_count{status=~\"[4|5]..\", job=\"orbilnot-kitchen\"}[30s])",
          "instant": false,
          "legendFormat": "__auto",
          "range": true,
          "refId": "errors count"
        }
      ],
      "title": " Error Rate",
      "type": "timeseries"
    },
    {
      "collapsed": true,
      "gridPos": {
        "h": 1,
        "w": 24,
        "x": 0,
        "y": 25
      },
      "id": 18,
      "panels": [
        {
          "datasource": {
            "default": true,
            "type": "prometheus",
            "uid": "ce6lrrt58z4zkc"
          },
          "description": "",
          "fieldConfig": {
            "defaults": {
              "color": {
                "mode": "palette-classic"
              },
              "custom": {
                "axisBorderShow": false,
                "axisCenteredZero": false,
                "axisColorMode": "text",
                "axisLabel": "",
                "axisPlacement": "auto",
                "barAlignment": 0,
                "barWidthFactor": 0.6,
                "drawStyle": "line",
                "fillOpacity": 0,
                "gradientMode": "none",
                "hideFrom": {
                  "legend": false,
                  "tooltip": false,
                  "viz": false
                },
                "insertNulls": false,
                "lineInterpolation": "linear",
                "lineStyle": {
                  "fill": "solid"
                },
                "lineWidth": 1,
                "pointSize": 5,
                "scaleDistribution": {
                  "type": "linear"
                },
                "showPoints": "auto",
                "spanNulls": false,
                "stacking": {
                  "group": "A",
                  "mode": "none"
                },
                "thresholdsStyle": {
                  "mode": "off"
                }
              },
              "mappings": [],
              "thresholds": {
                "mode": "absolute",
                "steps": [
                  {
                    "color": "green",
                    "value": null
                  },
                  {
                    "color": "red",
                    "value": 80
                  }
                ]
              }
            },
            "overrides": []
          },
          "gridPos": {
            "h": 8,
            "w": 12,
            "x": 0,
            "y": 25
          },
          "id": 17,
          "options": {
            "legend": {
              "calcs": [],
              "displayMode": "list",
              "placement": "bottom",
              "showLegend": true
            },
            "tooltip": {
              "mode": "single",
              "sort": "none"
            }
          },
          "targets": [
            {
              "datasource": {
                "type": "prometheus"
              },
              "editorMode": "code",
              "expr": "sum by (uri)(histogram_quantile(0.99, sum(rate(http_server_requests_seconds_bucket{ status!~\"5..\", job=\"orbilnot-foodstuff\"}[1m])) by (le)))",
              "hide": false,
              "instant": false,
              "legendFormat": "__auto",
              "range": true,
              "refId": "99_latency"
            },
            {
              "datasource": {
                "type": "prometheus"
              },
              "editorMode": "code",
              "expr": "sum by (uri) (histogram_quantile(0.95, sum(rate(http_server_requests_seconds_bucket{ status!~\"5..\", uri=~\"/user.*\"}[1m])) by (le)))",
              "hide": false,
              "instant": false,
              "legendFormat": "__auto",
              "range": true,
              "refId": "95_latency"
            },
            {
              "datasource": {
                "type": "prometheus"
              },
              "editorMode": "code",
              "expr": "sum by (uri) (histogram_quantile(0.50, sum(rate(http_server_requests_seconds_bucket{ status!~\"5..\", uri=~\"/user.*\"}[1m])) by (le)))",
              "hide": false,
              "instant": false,
              "legendFormat": "__auto",
              "range": true,
              "refId": "50_latency"
            }
          ],
          "title": "latency",
          "type": "timeseries"
        },
        {
          "datasource": {
            "default": true,
            "type": "prometheus",
            "uid": "ce6lrrt58z4zkc"
          },
          "description": "",
          "fieldConfig": {
            "defaults": {
              "color": {
                "mode": "palette-classic"
              },
              "custom": {
                "axisBorderShow": false,
                "axisCenteredZero": false,
                "axisColorMode": "text",
                "axisLabel": "",
                "axisPlacement": "auto",
                "barAlignment": 0,
                "barWidthFactor": 0.6,
                "drawStyle": "line",
                "fillOpacity": 0,
                "gradientMode": "none",
                "hideFrom": {
                  "legend": false,
                  "tooltip": false,
                  "viz": false
                },
                "insertNulls": false,
                "lineInterpolation": "linear",
                "lineWidth": 1,
                "pointSize": 5,
                "scaleDistribution": {
                  "type": "linear"
                },
                "showPoints": "auto",
                "spanNulls": false,
                "stacking": {
                  "group": "A",
                  "mode": "none"
                },
                "thresholdsStyle": {
                  "mode": "off"
                }
              },
              "mappings": [],
              "thresholds": {
                "mode": "absolute",
                "steps": [
                  {
                    "color": "green",
                    "value": null
                  },
                  {
                    "color": "red",
                    "value": 80
                  }
                ]
              }
            },
            "overrides": []
          },
          "gridPos": {
            "h": 8,
            "w": 12,
            "x": 0,
            "y": 33
          },
          "id": 15,
          "options": {
            "legend": {
              "calcs": [],
              "displayMode": "list",
              "placement": "bottom",
              "showLegend": true
            },
            "tooltip": {
              "mode": "single",
              "sort": "none"
            }
          },
          "targets": [
            {
              "datasource": {
                "type": "prometheus"
              },
              "disableTextWrap": false,
              "editorMode": "code",
              "expr": "irate(http_server_requests_seconds_count{job=\"orbilnot-foodstuff\"}[30s])",
              "fullMetaSearch": false,
              "includeNullMetadata": true,
              "instant": false,
              "legendFormat": "__auto",
              "range": true,
              "refId": "A",
              "useBackend": false
            }
          ],
          "title": "RPS",
          "type": "timeseries"
        },
        {
          "datasource": {
            "default": true,
            "type": "prometheus",
            "uid": "ce6lrrt58z4zkc"
          },
          "description": "",
          "fieldConfig": {
            "defaults": {
              "color": {
                "mode": "palette-classic"
              },
              "custom": {
                "axisBorderShow": false,
                "axisCenteredZero": false,
                "axisColorMode": "text",
                "axisLabel": "",
                "axisPlacement": "auto",
                "barAlignment": 0,
                "barWidthFactor": 0.6,
                "drawStyle": "line",
                "fillOpacity": 0,
                "gradientMode": "none",
                "hideFrom": {
                  "legend": false,
                  "tooltip": false,
                  "viz": false
                },
                "insertNulls": false,
                "lineInterpolation": "linear",
                "lineWidth": 1,
                "pointSize": 5,
                "scaleDistribution": {
                  "type": "linear"
                },
                "showPoints": "auto",
                "spanNulls": false,
                "stacking": {
                  "group": "A",
                  "mode": "none"
                },
                "thresholdsStyle": {
                  "mode": "off"
                }
              },
              "mappings": [],
              "thresholds": {
                "mode": "absolute",
                "steps": [
                  {
                    "color": "green",
                    "value": null
                  },
                  {
                    "color": "red",
                    "value": 80
                  }
                ]
              }
            },
            "overrides": []
          },
          "gridPos": {
            "h": 8,
            "w": 12,
            "x": 0,
            "y": 41
          },
          "id": 13,
          "options": {
            "legend": {
              "calcs": [],
              "displayMode": "list",
              "placement": "bottom",
              "showLegend": true
            },
            "tooltip": {
              "mode": "single",
              "sort": "none"
            }
          },
          "targets": [
            {
              "datasource": {
                "type": "prometheus"
              },
              "editorMode": "code",
              "expr": "irate(http_server_requests_seconds_count{status=~\"[4|5]..\", job=\"orbilnot-foodstuff\"}[30s])",
              "instant": false,
              "legendFormat": "__auto",
              "range": true,
              "refId": "errors count"
            }
          ],
          "title": " Error Rate",
          "type": "timeseries"
        }
      ],
      "title": "Foodstuff",
      "type": "row"
    },
    {
      "collapsed": false,
      "gridPos": {
        "h": 1,
        "w": 24,
        "x": 0,
        "y": 26
      },
      "id": 11,
      "panels": [],
      "title": "Billing",
      "type": "row"
    },
    {
      "datasource": {
        "default": true,
        "type": "prometheus",
        "uid": "ce6lrrt58z4zkc"
      },
      "description": "",
      "fieldConfig": {
        "defaults": {
          "color": {
            "mode": "palette-classic"
          },
          "custom": {
            "axisBorderShow": false,
            "axisCenteredZero": false,
            "axisColorMode": "text",
            "axisLabel": "",
            "axisPlacement": "auto",
            "barAlignment": 0,
            "barWidthFactor": 0.6,
            "drawStyle": "line",
            "fillOpacity": 0,
            "gradientMode": "none",
            "hideFrom": {
              "legend": false,
              "tooltip": false,
              "viz": false
            },
            "insertNulls": false,
            "lineInterpolation": "linear",
            "lineStyle": {
              "fill": "solid"
            },
            "lineWidth": 1,
            "pointSize": 5,
            "scaleDistribution": {
              "type": "linear"
            },
            "showPoints": "auto",
            "spanNulls": false,
            "stacking": {
              "group": "A",
              "mode": "none"
            },
            "thresholdsStyle": {
              "mode": "off"
            }
          },
          "mappings": [],
          "thresholds": {
            "mode": "absolute",
            "steps": [
              {
                "color": "green",
                "value": null
              },
              {
                "color": "red",
                "value": 80
              }
            ]
          }
        },
        "overrides": [
          {
            "__systemRef": "hideSeriesFrom",
            "matcher": {
              "id": "byNames",
              "options": {
                "mode": "exclude",
                "names": [
                  "sum by (uri)(histogram_quantile(0.99, sum(rate(http_server_requests_seconds_bucket{ status!~\"5..\", job=\"orbilnot-billing\"}[1m])) by (le)))"
                ],
                "prefix": "All except:",
                "readOnly": true
              }
            },
            "properties": [
              {
                "id": "custom.hideFrom",
                "value": {
                  "legend": false,
                  "tooltip": false,
                  "viz": true
                }
              }
            ]
          }
        ]
      },
      "gridPos": {
        "h": 8,
        "w": 12,
        "x": 0,
        "y": 27
      },
      "id": 10,
      "options": {
        "legend": {
          "calcs": [],
          "displayMode": "list",
          "placement": "bottom",
          "showLegend": true
        },
        "tooltip": {
          "mode": "single",
          "sort": "none"
        }
      },
      "targets": [
        {
          "datasource": {
            "type": "prometheus"
          },
          "editorMode": "code",
          "expr": "sum by (uri)(histogram_quantile(0.99, sum(rate(http_server_requests_seconds_bucket{ status!~\"5..\", job=\"orbilnot-billing\"}[1m])) by (le)))",
          "hide": false,
          "instant": false,
          "legendFormat": "__auto",
          "range": true,
          "refId": "99_latency"
        },
        {
          "datasource": {
            "type": "prometheus"
          },
          "editorMode": "code",
          "expr": "sum by (uri) (histogram_quantile(0.95, sum(rate(http_server_requests_seconds_bucket{ status!~\"5..\", uri=~\"/user.*\"}[1m])) by (le)))",
          "hide": false,
          "instant": false,
          "legendFormat": "__auto",
          "range": true,
          "refId": "95_latency"
        },
        {
          "datasource": {
            "type": "prometheus"
          },
          "editorMode": "code",
          "expr": "sum by (uri) (histogram_quantile(0.50, sum(rate(http_server_requests_seconds_bucket{ status!~\"5..\", uri=~\"/user.*\"}[1m])) by (le)))",
          "hide": false,
          "instant": false,
          "legendFormat": "__auto",
          "range": true,
          "refId": "50_latency"
        }
      ],
      "title": "latency",
      "type": "timeseries"
    },
    {
      "datasource": {
        "default": true,
        "type": "prometheus",
        "uid": "ce6lrrt58z4zkc"
      },
      "description": "",
      "fieldConfig": {
        "defaults": {
          "color": {
            "mode": "palette-classic"
          },
          "custom": {
            "axisBorderShow": false,
            "axisCenteredZero": false,
            "axisColorMode": "text",
            "axisLabel": "",
            "axisPlacement": "auto",
            "barAlignment": 0,
            "barWidthFactor": 0.6,
            "drawStyle": "line",
            "fillOpacity": 0,
            "gradientMode": "none",
            "hideFrom": {
              "legend": false,
              "tooltip": false,
              "viz": false
            },
            "insertNulls": false,
            "lineInterpolation": "linear",
            "lineWidth": 1,
            "pointSize": 5,
            "scaleDistribution": {
              "type": "linear"
            },
            "showPoints": "auto",
            "spanNulls": false,
            "stacking": {
              "group": "A",
              "mode": "none"
            },
            "thresholdsStyle": {
              "mode": "off"
            }
          },
          "mappings": [],
          "thresholds": {
            "mode": "absolute",
            "steps": [
              {
                "color": "green",
                "value": null
              },
              {
                "color": "red",
                "value": 80
              }
            ]
          }
        },
        "overrides": []
      },
      "gridPos": {
        "h": 8,
        "w": 12,
        "x": 0,
        "y": 35
      },
      "id": 8,
      "options": {
        "legend": {
          "calcs": [],
          "displayMode": "list",
          "placement": "bottom",
          "showLegend": true
        },
        "tooltip": {
          "mode": "single",
          "sort": "none"
        }
      },
      "targets": [
        {
          "datasource": {
            "type": "prometheus"
          },
          "disableTextWrap": false,
          "editorMode": "code",
          "expr": "irate(http_server_requests_seconds_count{job=\"orbilnot-billing\"}[30s])",
          "fullMetaSearch": false,
          "includeNullMetadata": true,
          "instant": false,
          "legendFormat": "__auto",
          "range": true,
          "refId": "A",
          "useBackend": false
        }
      ],
      "title": "RPS",
      "type": "timeseries"
    },
    {
      "datasource": {
        "default": true,
        "type": "prometheus",
        "uid": "ce6lrrt58z4zkc"
      },
      "description": "",
      "fieldConfig": {
        "defaults": {
          "color": {
            "mode": "palette-classic"
          },
          "custom": {
            "axisBorderShow": false,
            "axisCenteredZero": false,
            "axisColorMode": "text",
            "axisLabel": "",
            "axisPlacement": "auto",
            "barAlignment": 0,
            "barWidthFactor": 0.6,
            "drawStyle": "line",
            "fillOpacity": 0,
            "gradientMode": "none",
            "hideFrom": {
              "legend": false,
              "tooltip": false,
              "viz": false
            },
            "insertNulls": false,
            "lineInterpolation": "linear",
            "lineWidth": 1,
            "pointSize": 5,
            "scaleDistribution": {
              "type": "linear"
            },
            "showPoints": "auto",
            "spanNulls": false,
            "stacking": {
              "group": "A",
              "mode": "none"
            },
            "thresholdsStyle": {
              "mode": "off"
            }
          },
          "mappings": [],
          "thresholds": {
            "mode": "absolute",
            "steps": [
              {
                "color": "green",
                "value": null
              },
              {
                "color": "red",
                "value": 80
              }
            ]
          }
        },
        "overrides": [
          {
            "__systemRef": "hideSeriesFrom",
            "matcher": {
              "id": "byNames",
              "options": {
                "mode": "exclude",
                "names": [
                  "{error=\"none\", exception=\"none\", instance=\"billing-orbilnot:80\", job=\"orbilnot-billing\", method=\"POST\", outcome=\"CLIENT_ERROR\", status=\"401\", uri=\"/\"}"
                ],
                "prefix": "All except:",
                "readOnly": true
              }
            },
            "properties": [
              {
                "id": "custom.hideFrom",
                "value": {
                  "legend": false,
                  "tooltip": false,
                  "viz": true
                }
              }
            ]
          }
        ]
      },
      "gridPos": {
        "h": 8,
        "w": 12,
        "x": 0,
        "y": 43
      },
      "id": 6,
      "options": {
        "legend": {
          "calcs": [],
          "displayMode": "list",
          "placement": "bottom",
          "showLegend": true
        },
        "tooltip": {
          "mode": "single",
          "sort": "none"
        }
      },
      "targets": [
        {
          "datasource": {
            "type": "prometheus"
          },
          "editorMode": "code",
          "expr": "irate(http_server_requests_seconds_count{status=~\"[4|5]..\", job=\"orbilnot-billing\"}[30s])",
          "instant": false,
          "legendFormat": "__auto",
          "range": true,
          "refId": "errors count"
        }
      ],
      "title": " Error Rate",
      "type": "timeseries"
    },
    {
      "collapsed": true,
      "gridPos": {
        "h": 1,
        "w": 24,
        "x": 0,
        "y": 51
      },
      "id": 4,
      "panels": [
        {
          "gridPos": {
            "h": 8,
            "w": 12,
            "x": 0,
            "y": 50
          },
          "id": 3,
          "libraryPanel": {
            "name": " Error Rate",
            "uid": "ae6lsf572nw1sf"
          },
          "title": " Error Rate"
        },
        {
          "gridPos": {
            "h": 8,
            "w": 12,
            "x": 0,
            "y": 58
          },
          "id": 2,
          "libraryPanel": {
            "name": "RPS",
            "uid": "be6lsfz7g8w00e"
          },
          "title": "RPS"
        },
        {
          "gridPos": {
            "h": 8,
            "w": 12,
            "x": 0,
            "y": 66
          },
          "id": 1,
          "libraryPanel": {
            "name": "latency",
            "uid": "de6lsgbl4mozkc"
          },
          "title": "latency"
        }
      ],
      "title": "Orders",
      "type": "row"
    }
  ],
  "refresh": "5s",
  "schemaVersion": 39,
  "tags": [],
  "templating": {
    "list": []
  },
  "time": {
    "from": "now-5m",
    "to": "now"
  },
  "timepicker": {},
  "timezone": "browser",
  "title": "Orbilnot Dashboard",
  "uid": "ddxeyi1gq2xhcc",
  "version": 15,
  "weekStart": ""
}